rawdog/__init__.py
rawdog/__main__.py
rawdog/config.py
rawdog/execute_script.py
rawdog/llm_client.py
rawdog/logging.py
rawdog/parsing.py
rawdog/prompts.py
rawdog/utils.py
rawdog_ai-0.1.6.dist-info/METADATA
rawdog_ai-0.1.6.dist-info/WHEEL
rawdog_ai-0.1.6.dist-info/entry_points.txt
rawdog_ai-0.1.6.dist-info/licenses/LICENSE
rawdog_ai-0.1.6.dist-info/RECORD
