Metadata-Version: 2.1
Name: rawdog-ai
Version: 0.1.6
Summary: An AI command-line assistant
Project-URL: Homepage, https://github.com/AbanteAI/rawdog
Project-URL: Issues, https://github.com/AbanteAI/rawdog/issues
License-File: LICENSE
Classifier: License :: OSI Approved :: MIT License
Classifier: Operating System :: OS Independent
Classifier: Programming Language :: Python :: 3
Requires-Python: >=3.8
Requires-Dist: litellm>=1.22.3
